SimpleTK/__init__.py
SimpleTK_Pepe_Java-1.4.0.dist-info/LICENSE
SimpleTK_Pepe_Java-1.4.0.dist-info/METADATA
SimpleTK_Pepe_Java-1.4.0.dist-info/WHEEL
SimpleTK_Pepe_Java-1.4.0.dist-info/top_level.txt
SimpleTK_Pepe_Java-1.4.0.dist-info/RECORD
