Metadata-Version: 2.1
Name: SimpleTK-Pepe-Java
Version: 1.4.0
Summary: SimpleTK is an "Simple" Tkinter
Home-page: https://github.com/Pepe-77777/SimpleTK
Author: Pepê Szabo Silva
Author-email: pepe.szabo.silva@gmail.com
License: UNKNOWN
Project-URL: Bug Tracker, https://github.com/Pepe-77777/SimpleTK/issues
Platform: UNKNOWN
Classifier: Programming Language :: Python :: 3
Classifier: License :: OSI Approved :: MIT License
Classifier: Operating System :: OS Independent
Requires-Python: >=3.6
License-File: LICENSE
